locally_excluded_files/__init__.py
locally_excluded_files/secret_acer_setup/__init__.py
locally_excluded_files/secret_acer_setup/acer_model_proxy.py
locally_excluded_files/secret_acer_setup/acer_train.py
locally_excluded_files/secret_acer_setup/buffer.py
locally_excluded_files/secret_acer_setup/run_secret_acer_setup.py
locally_excluded_files/secret_acer_setup/runner.py
secret/__init__.py
secret/secret_acer_setup/__init__.py
secret/secret_acer_setup/acer_model_proxy.py
secret/secret_acer_setup/acer_train.py
secret/secret_acer_setup/buffer.py
secret/secret_acer_setup/run_secret_acer_setup.py
secret/secret_acer_setup/runner.py
vel/__init__.py
vel/exceptions.py
vel/launcher.py
vel/api/__init__.py
vel/api/info.py
vel/api/learner.py
vel/api/model_config.py
vel/api/base/__init__.py
vel/api/base/callback.py
vel/api/base/model.py
vel/api/base/model_factory.py
vel/api/base/optimizer.py
vel/api/base/schedule.py
vel/api/base/scheduler.py
vel/api/base/source.py
vel/api/base/storage.py
vel/api/base/train_phase.py
vel/api/data/__init__.py
vel/api/data/augmentation.py
vel/api/data/dataflow.py
vel/api/data/image_ops.py
vel/api/metrics/__init__.py
vel/api/metrics/averaging_metric.py
vel/api/metrics/base_metric.py
vel/api/metrics/summing_metric.py
vel/api/metrics/value_metric.py
vel/augmentations/__init__.py
vel/augmentations/center_crop.py
vel/augmentations/normalize.py
vel/augmentations/random_crop.py
vel/augmentations/random_horizontal_flip.py
vel/augmentations/random_lighting.py
vel/augmentations/random_rotate.py
vel/augmentations/random_scale.py
vel/augmentations/scale_min_size.py
vel/augmentations/to_array.py
vel/augmentations/to_tensor.py
vel/augmentations/tta/__init__.py
vel/augmentations/tta/train_tta.py
vel/callbacks/__init__.py
vel/callbacks/time_tracker.py
vel/commands/__init__.py
vel/commands/augvis_command.py
vel/commands/lr_find_command.py
vel/commands/phase_train_command.py
vel/commands/summary_command.py
vel-0.2.2.dist-info/METADATA
vel-0.2.2.dist-info/RECORD
vel-0.2.2.dist-info/WHEEL
vel-0.2.2.dist-info/entry_points.txt
vel-0.2.2.dist-info/top_level.txt
