Metadata-Version: 2.1
Name: vel
Version: 0.2.2
Summary: Velocity in deep-learning research
Home-page: https://github.com/MillionIntegrals/vel
Author: Jerry Tworek
Author-email: jerry@millionintegrals.com
License: MIT
Platform: UNKNOWN
Classifier: Development Status :: 3 - Alpha
Classifier: Intended Audience :: Developers
Classifier: Intended Audience :: Education
Classifier: Intended Audience :: Science/Research
Classifier: License :: OSI Approved :: MIT License
Classifier: Programming Language :: Python :: 3
Classifier: Programming Language :: Python :: 3.6
Classifier: Programming Language :: Python :: 3.7
Classifier: Topic :: Software Development :: Libraries
Classifier: Topic :: Software Development :: Libraries :: Python Modules
Requires-Python: >=3.6
Provides-Extra: mongo
Provides-Extra: mujoco
Provides-Extra: gym
Provides-Extra: dev
Provides-Extra: visdom
Requires-Dist: attrs
Requires-Dist: cloudpickle
Requires-Dist: numpy
Requires-Dist: opencv-python
Requires-Dist: pandas
Requires-Dist: pyyaml
Requires-Dist: scikit-learn
Requires-Dist: torch (==0.4.1)
Requires-Dist: torchvision
Requires-Dist: tqdm
Provides-Extra: dev
Requires-Dist: nose; extra == 'dev'
Provides-Extra: gym
Requires-Dist: gym[box2d,atari,classic_control]; extra == 'gym'
Provides-Extra: mongo
Requires-Dist: pymongo; extra == 'mongo'
Requires-Dist: dnspython; extra == 'mongo'
Provides-Extra: mujoco
Requires-Dist: gym[robotics,mujoco]; extra == 'mujoco'
Provides-Extra: visdom
Requires-Dist: visdom; extra == 'visdom'
